[{"date":"2024-03-25","year":2020,"make":"B M W","model":"M SERIES","trim":"M5 4D SEDAN COMPETITION","price":63394,"miles":36700,"dev":6660},{"date":"2024-04-01","year":2020,"make":"B M W","model":"M SERIES","trim":"M5 4D SEDAN COMPETITION","price":62004,"miles":36900,"dev":6660},{"date":"2024-04-08","year":2020,"make":"B M W","model":"M SERIES","trim":"M5 4D SEDAN COMPETITION","price":61350,"miles":37100,"dev":6660},{"date":"2024-04-15","year":2020,"make":"B M W","model":"M SERIES","trim":"M5 4D SEDAN COMPETITION","price":61014,"miles":37300,"dev":6660},{"date":"2024-04-22","year":2020,"make":"B M W","model":"M SERIES","trim":"M5 4D SEDAN COMPETITION","price":60921,"miles":37500,"dev":6660},{"date":"2024-04-29","year":2020,"make":"B M W","model":"M SERIES","trim":"M5 4D SEDAN COMPETITION","price":60945,"miles":37700,"dev":6660},{"date":"2024-05-06","year":2020,"make":"B M W","model":"M SERIES","trim":"M5 4D SEDAN COMPETITION","price":60964,"miles":37900,"dev":6660},{"date":"2024-05-13","year":2020,"make":"B M W","model":"M SERIES","trim":"M5 4D SEDAN COMPETITION","price":60884,"miles":38100,"dev":6660},{"date":"2024-05-20","year":2020,"make":"B M W","model":"M SERIES","trim":"M5 4D SEDAN COMPETITION","price":60722,"miles":38200,"dev":6660},{"date":"2024-05-27","year":2020,"make":"B M W","model":"M SERIES","trim":"M5 4D SEDAN COMPETITION","price":60514,"miles":38400,"dev":6660},{"date":"2024-06-03","year":2020,"make":"B M W","model":"M SERIES","trim":"M5 4D SEDAN COMPETITION","price":60304,"miles":38600,"dev":6660},{"date":"2024-06-10","year":2020,"make":"B M W","model":"M SERIES","trim":"M5 4D SEDAN COMPETITION","price":60123,"miles":38800,"dev":6660},{"date":"2024-06-17","year":2020,"make":"B M W","model":"M SERIES","trim":"M5 4D SEDAN COMPETITION","price":59963,"miles":39000,"dev":6660},{"date":"2024-06-24","year":2020,"make":"B M W","model":"M SERIES","trim":"M5 4D SEDAN COMPETITION","price":59807,"miles":39200,"dev":6660},{"date":"2024-07-01","year":2020,"make":"B M W","model":"M SERIES","trim":"M5 4D SEDAN COMPETITION","price":59637,"miles":39400,"dev":6660},{"date":"2024-07-08","year":2020,"make":"B M W","model":"M SERIES","trim":"M5 4D SEDAN COMPETITION","price":59441,"miles":39600,"dev":6660},{"date":"2024-07-15","year":2020,"make":"B M W","model":"M SERIES","trim":"M5 4D SEDAN COMPETITION","price":59228,"miles":39700,"dev":6660},{"date":"2024-07-22","year":2020,"make":"B M W","model":"M SERIES","trim":"M5 4D SEDAN COMPETITION","price":59007,"miles":39900,"dev":6660},{"date":"2024-07-29","year":2020,"make":"B M W","model":"M SERIES","trim":"M5 4D SEDAN COMPETITION","price":58791,"miles":40100,"dev":6660},{"date":"2024-08-05","year":2020,"make":"B M W","model":"M SERIES","trim":"M5 4D SEDAN COMPETITION","price":58592,"miles":40300,"dev":6660},{"date":"2024-08-12","year":2020,"make":"B M W","model":"M SERIES","trim":"M5 4D SEDAN COMPETITION","price":58413,"miles":40500,"dev":6660},{"date":"2024-08-19","year":2020,"make":"B M W","model":"M SERIES","trim":"M5 4D SEDAN COMPETITION","price":58258,"miles":40700,"dev":6660},{"date":"2024-08-26","year":2020,"make":"B M W","model":"M SERIES","trim":"M5 4D SEDAN COMPETITION","price":58130,"miles":40900,"dev":6660},{"date":"2024-09-02","year":2020,"make":"B M W","model":"M SERIES","trim":"M5 4D SEDAN COMPETITION","price":58028,"miles":41000,"dev":6660},{"date":"2024-09-09","year":2020,"make":"B M W","model":"M SERIES","trim":"M5 4D SEDAN COMPETITION","price":57934,"miles":41200,"dev":6660},{"date":"2024-09-16","year":2020,"make":"B M W","model":"M SERIES","trim":"M5 4D SEDAN COMPETITION","price":57822,"miles":41400,"dev":6660},{"date":"2024-09-23","year":2020,"make":"B M W","model":"M SERIES","trim":"M5 4D SEDAN COMPETITION","price":57671,"miles":41600,"dev":6660},{"date":"2024-09-30","year":2020,"make":"B M W","model":"M SERIES","trim":"M5 4D SEDAN COMPETITION","price":57467,"miles":41800,"dev":6660},{"date":"2024-10-07","year":2020,"make":"B M W","model":"M SERIES","trim":"M5 4D SEDAN COMPETITION","price":57240,"miles":42000,"dev":6660},{"date":"2024-10-14","year":2020,"make":"B M W","model":"M SERIES","trim":"M5 4D SEDAN COMPETITION","price":57029,"miles":42200,"dev":6660},{"date":"2024-10-21","year":2020,"make":"B M W","model":"M SERIES","trim":"M5 4D SEDAN COMPETITION","price":56873,"miles":42400,"dev":6660},{"date":"2024-10-28","year":2020,"make":"B M W","model":"M SERIES","trim":"M5 4D SEDAN COMPETITION","price":56789,"miles":42500,"dev":6660},{"date":"2024-11-04","year":2020,"make":"B M W","model":"M SERIES","trim":"M5 4D SEDAN COMPETITION","price":56735,"miles":42700,"dev":6660},{"date":"2024-11-11","year":2020,"make":"B M W","model":"M SERIES","trim":"M5 4D SEDAN COMPETITION","price":56647,"miles":42900,"dev":6660},{"date":"2024-11-18","year":2020,"make":"B M W","model":"M SERIES","trim":"M5 4D SEDAN COMPETITION","price":56460,"miles":43100,"dev":6660},{"date":"2024-11-25","year":2020,"make":"B M W","model":"M SERIES","trim":"M5 4D SEDAN COMPETITION","price":56137,"miles":43300,"dev":6660},{"date":"2024-12-02","year":2020,"make":"B M W","model":"M SERIES","trim":"M5 4D SEDAN COMPETITION","price":55719,"miles":43500,"dev":6660},{"date":"2024-12-09","year":2020,"make":"B M W","model":"M SERIES","trim":"M5 4D SEDAN COMPETITION","price":55271,"miles":43700,"dev":6660},{"date":"2024-12-16","year":2020,"make":"B M W","model":"M SERIES","trim":"M5 4D SEDAN COMPETITION","price":54854,"miles":43900,"dev":6660},{"date":"2024-12-23","year":2020,"make":"B M W","model":"M SERIES","trim":"M5 4D SEDAN COMPETITION","price":54511,"miles":44000,"dev":6660},{"date":"2024-12-30","year":2020,"make":"B M W","model":"M SERIES","trim":"M5 4D SEDAN COMPETITION","price":54244,"miles":44200,"dev":6660},{"date":"2025-01-06","year":2020,"make":"B M W","model":"M SERIES","trim":"M5 4D SEDAN COMPETITION","price":54110,"miles":44400,"dev":6660},{"date":"2025-01-13","year":2020,"make":"B M W","model":"M SERIES","trim":"M5 4D SEDAN COMPETITION","price":53836,"miles":44600,"dev":6660},{"date":"2025-01-20","year":2020,"make":"B M W","model":"M SERIES","trim":"M5 4D SEDAN COMPETITION","price":53526,"miles":44800,"dev":6660},{"date":"2025-01-27","year":2020,"make":"B M W","model":"M SERIES","trim":"M5 4D SEDAN COMPETITION","price":53216,"miles":45000,"dev":6660},{"date":"2025-02-03","year":2020,"make":"B M W","model":"M SERIES","trim":"M5 4D SEDAN COMPETITION","price":52953,"miles":45200,"dev":6660},{"date":"2025-02-10","year":2020,"make":"B M W","model":"M SERIES","trim":"M5 4D SEDAN COMPETITION","price":52775,"miles":45300,"dev":6660},{"date":"2025-02-17","year":2020,"make":"B M W","model":"M SERIES","trim":"M5 4D SEDAN COMPETITION","price":52745,"miles":45500,"dev":6660},{"date":"2025-02-24","year":2020,"make":"B M W","model":"M SERIES","trim":"M5 4D SEDAN COMPETITION","price":52867,"miles":45700,"dev":6660},{"date":"2025-03-03","year":2020,"make":"B M W","model":"M SERIES","trim":"M5 4D SEDAN COMPETITION","price":53035,"miles":45900,"dev":6660},{"date":"2025-03-10","year":2020,"make":"B M W","model":"M SERIES","trim":"M5 4D SEDAN COMPETITION","price":53114,"miles":46100,"dev":6660},{"date":"2025-03-17","year":2020,"make":"B M W","model":"M SERIES","trim":"M5 4D SEDAN COMPETITION","price":52970,"miles":46300,"dev":6660},{"date":"2025-03-24","year":2020,"make":"B M W","model":"M SERIES","trim":"M5 4D SEDAN COMPETITION","price":52522,"miles":46500,"dev":6660},{"date":"2025-03-31","year":2020,"make":"B M W","model":"M SERIES","trim":"M5 4D SEDAN COMPETITION","price":51413,"miles":46700,"dev":6660},{"date":"2025-04-07","year":2020,"make":"B M W","model":"M SERIES","trim":"M5 4D SEDAN COMPETITION","price":50873,"miles":46800,"dev":6660},{"date":"2025-04-14","year":2020,"make":"B M W","model":"M SERIES","trim":"M5 4D SEDAN COMPETITION","price":50593,"miles":47000,"dev":6660},{"date":"2025-04-21","year":2020,"make":"B M W","model":"M SERIES","trim":"M5 4D SEDAN COMPETITION","price":50504,"miles":47200,"dev":6660},{"date":"2025-04-28","year":2020,"make":"B M W","model":"M SERIES","trim":"M5 4D SEDAN COMPETITION","price":50507,"miles":47400,"dev":6660},{"date":"2025-05-05","year":2020,"make":"B M W","model":"M SERIES","trim":"M5 4D SEDAN COMPETITION","price":50506,"miles":47600,"dev":6660},{"date":"2025-05-12","year":2020,"make":"B M W","model":"M SERIES","trim":"M5 4D SEDAN COMPETITION","price":50427,"miles":47800,"dev":6660},{"date":"2025-05-19","year":2020,"make":"B M W","model":"M SERIES","trim":"M5 4D SEDAN COMPETITION","price":50281,"miles":48000,"dev":6660},{"date":"2025-05-26","year":2020,"make":"B M W","model":"M SERIES","trim":"M5 4D SEDAN COMPETITION","price":50102,"miles":48200,"dev":6660},{"date":"2025-06-02","year":2020,"make":"B M W","model":"M SERIES","trim":"M5 4D SEDAN COMPETITION","price":49909,"miles":48300,"dev":6660},{"date":"2025-06-09","year":2020,"make":"B M W","model":"M SERIES","trim":"M5 4D SEDAN COMPETITION","price":49751,"miles":48500,"dev":6660},{"date":"2025-06-16","year":2020,"make":"B M W","model":"M SERIES","trim":"M5 4D SEDAN COMPETITION","price":49610,"miles":48700,"dev":6660},{"date":"2025-06-23","year":2020,"make":"B M W","model":"M SERIES","trim":"M5 4D SEDAN COMPETITION","price":49472,"miles":48900,"dev":6660},{"date":"2025-06-30","year":2020,"make":"B M W","model":"M SERIES","trim":"M5 4D SEDAN COMPETITION","price":49323,"miles":49100,"dev":6660},{"date":"2025-07-07","year":2020,"make":"B M W","model":"M SERIES","trim":"M5 4D SEDAN COMPETITION","price":49155,"miles":49300,"dev":6660},{"date":"2025-07-14","year":2020,"make":"B M W","model":"M SERIES","trim":"M5 4D SEDAN COMPETITION","price":48972,"miles":49500,"dev":6660},{"date":"2025-07-21","year":2020,"make":"B M W","model":"M SERIES","trim":"M5 4D SEDAN COMPETITION","price":48784,"miles":49700,"dev":6660},{"date":"2025-07-28","year":2020,"make":"B M W","model":"M SERIES","trim":"M5 4D SEDAN COMPETITION","price":48584,"miles":49800,"dev":6660},{"date":"2025-08-04","year":2020,"make":"B M W","model":"M SERIES","trim":"M5 4D SEDAN COMPETITION","price":48413,"miles":50000,"dev":6660},{"date":"2025-08-11","year":2020,"make":"B M W","model":"M SERIES","trim":"M5 4D SEDAN COMPETITION","price":48258,"miles":50200,"dev":6660},{"date":"2025-08-18","year":2020,"make":"B M W","model":"M SERIES","trim":"M5 4D SEDAN COMPETITION","price":48122,"miles":50400,"dev":6660},{"date":"2025-08-25","year":2020,"make":"B M W","model":"M SERIES","trim":"M5 4D SEDAN COMPETITION","price":48007,"miles":50600,"dev":6660},{"date":"2025-09-01","year":2020,"make":"B M W","model":"M SERIES","trim":"M5 4D SEDAN COMPETITION","price":47913,"miles":50800,"dev":6660},{"date":"2025-09-08","year":2020,"make":"B M W","model":"M SERIES","trim":"M5 4D SEDAN COMPETITION","price":47824,"miles":51000,"dev":6660},{"date":"2025-09-15","year":2020,"make":"B M W","model":"M SERIES","trim":"M5 4D SEDAN COMPETITION","price":47704,"miles":51100,"dev":6660},{"date":"2025-09-22","year":2020,"make":"B M W","model":"M SERIES","trim":"M5 4D SEDAN COMPETITION","price":47571,"miles":51300,"dev":6660},{"date":"2025-09-29","year":2020,"make":"B M W","model":"M SERIES","trim":"M5 4D SEDAN COMPETITION","price":47397,"miles":51500,"dev":6660},{"date":"2025-10-06","year":2020,"make":"B M W","model":"M SERIES","trim":"M5 4D SEDAN COMPETITION","price":47206,"miles":51700,"dev":6660},{"date":"2025-10-13","year":2020,"make":"B M W","model":"M SERIES","trim":"M5 4D SEDAN COMPETITION","price":47028,"miles":51900,"dev":6660},{"date":"2025-10-20","year":2020,"make":"B M W","model":"M SERIES","trim":"M5 4D SEDAN COMPETITION","price":46891,"miles":52100,"dev":6660},{"date":"2025-10-27","year":2020,"make":"B M W","model":"M SERIES","trim":"M5 4D SEDAN COMPETITION","price":46813,"miles":52300,"dev":6660},{"date":"2025-11-03","year":2020,"make":"B M W","model":"M SERIES","trim":"M5 4D SEDAN COMPETITION","price":46757,"miles":52500,"dev":6660},{"date":"2025-11-10","year":2020,"make":"B M W","model":"M SERIES","trim":"M5 4D SEDAN COMPETITION","price":46652,"miles":52600,"dev":6660},{"date":"2025-11-17","year":2020,"make":"B M W","model":"M SERIES","trim":"M5 4D SEDAN COMPETITION","price":46493,"miles":52800,"dev":6660},{"date":"2025-11-24","year":2020,"make":"B M W","model":"M SERIES","trim":"M5 4D SEDAN COMPETITION","price":46228,"miles":53000,"dev":6660},{"date":"2025-12-01","year":2020,"make":"B M W","model":"M SERIES","trim":"M5 4D SEDAN COMPETITION","price":45890,"miles":53200,"dev":6660},{"date":"2025-12-08","year":2020,"make":"B M W","model":"M SERIES","trim":"M5 4D SEDAN COMPETITION","price":45529,"miles":53400,"dev":6660},{"date":"2025-12-15","year":2020,"make":"B M W","model":"M SERIES","trim":"M5 4D SEDAN COMPETITION","price":45193,"miles":53600,"dev":6660},{"date":"2025-12-22","year":2020,"make":"B M W","model":"M SERIES","trim":"M5 4D SEDAN COMPETITION","price":44918,"miles":53800,"dev":6660},{"date":"2025-12-29","year":2020,"make":"B M W","model":"M SERIES","trim":"M5 4D SEDAN COMPETITION","price":44698,"miles":54000,"dev":6660},{"date":"2026-01-05","year":2020,"make":"B M W","model":"M SERIES","trim":"M5 4D SEDAN COMPETITION","price":44557,"miles":54100,"dev":6660},{"date":"2026-01-12","year":2020,"make":"B M W","model":"M SERIES","trim":"M5 4D SEDAN COMPETITION","price":44332,"miles":54300,"dev":6660},{"date":"2026-01-19","year":2020,"make":"B M W","model":"M SERIES","trim":"M5 4D SEDAN COMPETITION","price":44079,"miles":54500,"dev":6660},{"date":"2026-01-26","year":2020,"make":"B M W","model":"M SERIES","trim":"M5 4D SEDAN COMPETITION","price":43826,"miles":54700,"dev":6660},{"date":"2026-02-02","year":2020,"make":"B M W","model":"M SERIES","trim":"M5 4D SEDAN COMPETITION","price":43609,"miles":54900,"dev":6660},{"date":"2026-02-09","year":2020,"make":"B M W","model":"M SERIES","trim":"M5 4D SEDAN COMPETITION","price":43465,"miles":55100,"dev":6660},{"date":"2026-02-16","year":2020,"make":"B M W","model":"M SERIES","trim":"M5 4D SEDAN COMPETITION","price":43428,"miles":55300,"dev":6660},{"date":"2026-02-23","year":2020,"make":"B M W","model":"M SERIES","trim":"M5 4D SEDAN COMPETITION","price":43483,"miles":55400,"dev":6660},{"date":"2026-03-02","year":2020,"make":"B M W","model":"M SERIES","trim":"M5 4D SEDAN COMPETITION","price":43598,"miles":55600,"dev":6660},{"date":"2026-03-09","year":2020,"make":"B M W","model":"M SERIES","trim":"M5 4D SEDAN COMPETITION","price":43644,"miles":55800,"dev":6660},{"date":"2026-03-16","year":2020,"make":"B M W","model":"M SERIES","trim":"M5 4D SEDAN COMPETITION","price":43520,"miles":56000,"dev":6660},{"date":"2026-03-23","year":2020,"make":"B M W","model":"M SERIES","trim":"M5 4D SEDAN COMPETITION","price":43162,"miles":56200,"dev":6660},{"date":"2026-03-30","year":2020,"make":"B M W","model":"M SERIES","trim":"M5 4D SEDAN COMPETITION","price":42299,"miles":56400,"dev":6660}]