[{"date":"2024-03-25","year":2018,"make":"AUDI","model":"TT","trim":"2D CONVERTIBLE","price":29003,"miles":30300,"dev":2625},{"date":"2024-04-01","year":2018,"make":"AUDI","model":"TT","trim":"2D CONVERTIBLE","price":28789,"miles":30400,"dev":2625},{"date":"2024-04-08","year":2018,"make":"AUDI","model":"TT","trim":"2D CONVERTIBLE","price":28585,"miles":30400,"dev":2625},{"date":"2024-04-15","year":2018,"make":"AUDI","model":"TT","trim":"2D CONVERTIBLE","price":28394,"miles":30500,"dev":2625},{"date":"2024-04-22","year":2018,"make":"AUDI","model":"TT","trim":"2D CONVERTIBLE","price":28214,"miles":30600,"dev":2625},{"date":"2024-04-29","year":2018,"make":"AUDI","model":"TT","trim":"2D CONVERTIBLE","price":28045,"miles":30600,"dev":2625},{"date":"2024-05-06","year":2018,"make":"AUDI","model":"TT","trim":"2D CONVERTIBLE","price":27889,"miles":30700,"dev":2625},{"date":"2024-05-13","year":2018,"make":"AUDI","model":"TT","trim":"2D CONVERTIBLE","price":27744,"miles":30800,"dev":2625},{"date":"2024-05-20","year":2018,"make":"AUDI","model":"TT","trim":"2D CONVERTIBLE","price":27611,"miles":30800,"dev":2625},{"date":"2024-05-27","year":2018,"make":"AUDI","model":"TT","trim":"2D CONVERTIBLE","price":27490,"miles":30900,"dev":2625},{"date":"2024-06-03","year":2018,"make":"AUDI","model":"TT","trim":"2D CONVERTIBLE","price":27380,"miles":31000,"dev":2625},{"date":"2024-06-10","year":2018,"make":"AUDI","model":"TT","trim":"2D CONVERTIBLE","price":27282,"miles":31000,"dev":2625},{"date":"2024-06-17","year":2018,"make":"AUDI","model":"TT","trim":"2D CONVERTIBLE","price":27194,"miles":31100,"dev":2625},{"date":"2024-06-24","year":2018,"make":"AUDI","model":"TT","trim":"2D CONVERTIBLE","price":27117,"miles":31100,"dev":2625},{"date":"2024-07-01","year":2018,"make":"AUDI","model":"TT","trim":"2D CONVERTIBLE","price":27050,"miles":31200,"dev":2625},{"date":"2024-07-08","year":2018,"make":"AUDI","model":"TT","trim":"2D CONVERTIBLE","price":26994,"miles":31300,"dev":2625},{"date":"2024-07-15","year":2018,"make":"AUDI","model":"TT","trim":"2D CONVERTIBLE","price":26948,"miles":31300,"dev":2625},{"date":"2024-07-22","year":2018,"make":"AUDI","model":"TT","trim":"2D CONVERTIBLE","price":26914,"miles":31400,"dev":2625},{"date":"2024-07-29","year":2018,"make":"AUDI","model":"TT","trim":"2D CONVERTIBLE","price":26898,"miles":31500,"dev":2625},{"date":"2024-08-05","year":2018,"make":"AUDI","model":"TT","trim":"2D CONVERTIBLE","price":26910,"miles":31500,"dev":2625},{"date":"2024-08-12","year":2018,"make":"AUDI","model":"TT","trim":"2D CONVERTIBLE","price":26954,"miles":31600,"dev":2625},{"date":"2024-08-19","year":2018,"make":"AUDI","model":"TT","trim":"2D CONVERTIBLE","price":27008,"miles":31700,"dev":2625},{"date":"2024-08-26","year":2018,"make":"AUDI","model":"TT","trim":"2D CONVERTIBLE","price":27066,"miles":31700,"dev":2625},{"date":"2024-09-02","year":2018,"make":"AUDI","model":"TT","trim":"2D CONVERTIBLE","price":27124,"miles":31800,"dev":2625},{"date":"2024-09-09","year":2018,"make":"AUDI","model":"TT","trim":"2D CONVERTIBLE","price":27177,"miles":31900,"dev":2625},{"date":"2024-09-16","year":2018,"make":"AUDI","model":"TT","trim":"2D CONVERTIBLE","price":27221,"miles":31900,"dev":2625},{"date":"2024-09-23","year":2018,"make":"AUDI","model":"TT","trim":"2D CONVERTIBLE","price":27255,"miles":32000,"dev":2625},{"date":"2024-09-30","year":2018,"make":"AUDI","model":"TT","trim":"2D CONVERTIBLE","price":27279,"miles":32100,"dev":2625},{"date":"2024-10-07","year":2018,"make":"AUDI","model":"TT","trim":"2D CONVERTIBLE","price":27295,"miles":32100,"dev":2625},{"date":"2024-10-14","year":2018,"make":"AUDI","model":"TT","trim":"2D CONVERTIBLE","price":27308,"miles":32200,"dev":2625},{"date":"2024-10-21","year":2018,"make":"AUDI","model":"TT","trim":"2D CONVERTIBLE","price":27322,"miles":32300,"dev":2625},{"date":"2024-10-28","year":2018,"make":"AUDI","model":"TT","trim":"2D CONVERTIBLE","price":27338,"miles":32300,"dev":2625},{"date":"2024-11-04","year":2018,"make":"AUDI","model":"TT","trim":"2D CONVERTIBLE","price":27357,"miles":32400,"dev":2625},{"date":"2024-11-11","year":2018,"make":"AUDI","model":"TT","trim":"2D CONVERTIBLE","price":27378,"miles":32500,"dev":2625},{"date":"2024-11-18","year":2018,"make":"AUDI","model":"TT","trim":"2D CONVERTIBLE","price":27396,"miles":32500,"dev":2625},{"date":"2024-11-25","year":2018,"make":"AUDI","model":"TT","trim":"2D CONVERTIBLE","price":27405,"miles":32600,"dev":2625},{"date":"2024-12-02","year":2018,"make":"AUDI","model":"TT","trim":"2D CONVERTIBLE","price":27399,"miles":32700,"dev":2625},{"date":"2024-12-09","year":2018,"make":"AUDI","model":"TT","trim":"2D CONVERTIBLE","price":27378,"miles":32700,"dev":2625},{"date":"2024-12-16","year":2018,"make":"AUDI","model":"TT","trim":"2D CONVERTIBLE","price":27342,"miles":32800,"dev":2625},{"date":"2024-12-23","year":2018,"make":"AUDI","model":"TT","trim":"2D CONVERTIBLE","price":27297,"miles":32900,"dev":2625},{"date":"2024-12-30","year":2018,"make":"AUDI","model":"TT","trim":"2D CONVERTIBLE","price":27249,"miles":32900,"dev":2625},{"date":"2025-01-06","year":2018,"make":"AUDI","model":"TT","trim":"2D CONVERTIBLE","price":27204,"miles":33000,"dev":2625},{"date":"2025-01-13","year":2018,"make":"AUDI","model":"TT","trim":"2D CONVERTIBLE","price":27168,"miles":33100,"dev":2625},{"date":"2025-01-20","year":2018,"make":"AUDI","model":"TT","trim":"2D CONVERTIBLE","price":27147,"miles":33100,"dev":2625},{"date":"2025-01-27","year":2018,"make":"AUDI","model":"TT","trim":"2D CONVERTIBLE","price":27145,"miles":33200,"dev":2625},{"date":"2025-02-03","year":2018,"make":"AUDI","model":"TT","trim":"2D CONVERTIBLE","price":27164,"miles":33300,"dev":2625},{"date":"2025-02-10","year":2018,"make":"AUDI","model":"TT","trim":"2D CONVERTIBLE","price":27197,"miles":33300,"dev":2625},{"date":"2025-02-17","year":2018,"make":"AUDI","model":"TT","trim":"2D CONVERTIBLE","price":27238,"miles":33400,"dev":2625},{"date":"2025-02-24","year":2018,"make":"AUDI","model":"TT","trim":"2D CONVERTIBLE","price":27279,"miles":33500,"dev":2625},{"date":"2025-03-03","year":2018,"make":"AUDI","model":"TT","trim":"2D CONVERTIBLE","price":27311,"miles":33500,"dev":2625},{"date":"2025-03-10","year":2018,"make":"AUDI","model":"TT","trim":"2D CONVERTIBLE","price":27330,"miles":33600,"dev":2625},{"date":"2025-03-17","year":2018,"make":"AUDI","model":"TT","trim":"2D CONVERTIBLE","price":27329,"miles":33700,"dev":2625},{"date":"2025-03-24","year":2018,"make":"AUDI","model":"TT","trim":"2D CONVERTIBLE","price":27307,"miles":33700,"dev":2625},{"date":"2025-03-31","year":2018,"make":"AUDI","model":"TT","trim":"2D CONVERTIBLE","price":27266,"miles":33800,"dev":2625},{"date":"2025-04-07","year":2018,"make":"AUDI","model":"TT","trim":"2D CONVERTIBLE","price":27206,"miles":33900,"dev":2625},{"date":"2025-04-14","year":2018,"make":"AUDI","model":"TT","trim":"2D CONVERTIBLE","price":27131,"miles":33900,"dev":2625},{"date":"2025-04-21","year":2018,"make":"AUDI","model":"TT","trim":"2D CONVERTIBLE","price":27038,"miles":34000,"dev":2625},{"date":"2025-04-28","year":2018,"make":"AUDI","model":"TT","trim":"2D CONVERTIBLE","price":26924,"miles":34100,"dev":2625},{"date":"2025-05-05","year":2018,"make":"AUDI","model":"TT","trim":"2D CONVERTIBLE","price":26786,"miles":34100,"dev":2625},{"date":"2025-05-12","year":2018,"make":"AUDI","model":"TT","trim":"2D CONVERTIBLE","price":26621,"miles":34200,"dev":2625},{"date":"2025-05-19","year":2018,"make":"AUDI","model":"TT","trim":"2D CONVERTIBLE","price":26429,"miles":34300,"dev":2625},{"date":"2025-05-26","year":2018,"make":"AUDI","model":"TT","trim":"2D CONVERTIBLE","price":26215,"miles":34300,"dev":2625},{"date":"2025-06-02","year":2018,"make":"AUDI","model":"TT","trim":"2D CONVERTIBLE","price":25989,"miles":34400,"dev":2625},{"date":"2025-06-09","year":2018,"make":"AUDI","model":"TT","trim":"2D CONVERTIBLE","price":25763,"miles":34400,"dev":2625},{"date":"2025-06-16","year":2018,"make":"AUDI","model":"TT","trim":"2D CONVERTIBLE","price":25555,"miles":34500,"dev":2625},{"date":"2025-06-23","year":2018,"make":"AUDI","model":"TT","trim":"2D CONVERTIBLE","price":25379,"miles":34600,"dev":2625},{"date":"2025-06-30","year":2018,"make":"AUDI","model":"TT","trim":"2D CONVERTIBLE","price":25250,"miles":34600,"dev":2625},{"date":"2025-07-07","year":2018,"make":"AUDI","model":"TT","trim":"2D CONVERTIBLE","price":25179,"miles":34700,"dev":2625},{"date":"2025-07-14","year":2018,"make":"AUDI","model":"TT","trim":"2D CONVERTIBLE","price":25170,"miles":34800,"dev":2625},{"date":"2025-07-21","year":2018,"make":"AUDI","model":"TT","trim":"2D CONVERTIBLE","price":25222,"miles":34800,"dev":2625},{"date":"2025-07-28","year":2018,"make":"AUDI","model":"TT","trim":"2D CONVERTIBLE","price":25327,"miles":34900,"dev":2625},{"date":"2025-08-04","year":2018,"make":"AUDI","model":"TT","trim":"2D CONVERTIBLE","price":25473,"miles":35000,"dev":2625},{"date":"2025-08-11","year":2018,"make":"AUDI","model":"TT","trim":"2D CONVERTIBLE","price":25648,"miles":35000,"dev":2625},{"date":"2025-08-18","year":2018,"make":"AUDI","model":"TT","trim":"2D CONVERTIBLE","price":25839,"miles":35100,"dev":2625},{"date":"2025-08-25","year":2018,"make":"AUDI","model":"TT","trim":"2D CONVERTIBLE","price":26032,"miles":35200,"dev":2625},{"date":"2025-09-01","year":2018,"make":"AUDI","model":"TT","trim":"2D CONVERTIBLE","price":26216,"miles":35200,"dev":2625},{"date":"2025-09-08","year":2018,"make":"AUDI","model":"TT","trim":"2D CONVERTIBLE","price":26375,"miles":35300,"dev":2625},{"date":"2025-09-15","year":2018,"make":"AUDI","model":"TT","trim":"2D CONVERTIBLE","price":26500,"miles":35400,"dev":2625},{"date":"2025-09-22","year":2018,"make":"AUDI","model":"TT","trim":"2D CONVERTIBLE","price":26588,"miles":35400,"dev":2625},{"date":"2025-09-29","year":2018,"make":"AUDI","model":"TT","trim":"2D CONVERTIBLE","price":26643,"miles":35500,"dev":2625},{"date":"2025-10-06","year":2018,"make":"AUDI","model":"TT","trim":"2D CONVERTIBLE","price":26669,"miles":35600,"dev":2625},{"date":"2025-10-13","year":2018,"make":"AUDI","model":"TT","trim":"2D CONVERTIBLE","price":26669,"miles":35600,"dev":2625},{"date":"2025-10-20","year":2018,"make":"AUDI","model":"TT","trim":"2D CONVERTIBLE","price":26641,"miles":35700,"dev":2625},{"date":"2025-10-27","year":2018,"make":"AUDI","model":"TT","trim":"2D CONVERTIBLE","price":26586,"miles":35800,"dev":2625},{"date":"2025-11-03","year":2018,"make":"AUDI","model":"TT","trim":"2D CONVERTIBLE","price":26503,"miles":35800,"dev":2625},{"date":"2025-11-10","year":2018,"make":"AUDI","model":"TT","trim":"2D CONVERTIBLE","price":26392,"miles":35900,"dev":2625},{"date":"2025-11-17","year":2018,"make":"AUDI","model":"TT","trim":"2D CONVERTIBLE","price":26255,"miles":36000,"dev":2625},{"date":"2025-11-24","year":2018,"make":"AUDI","model":"TT","trim":"2D CONVERTIBLE","price":26095,"miles":36000,"dev":2625},{"date":"2025-12-01","year":2018,"make":"AUDI","model":"TT","trim":"2D CONVERTIBLE","price":25914,"miles":36100,"dev":2625},{"date":"2025-12-08","year":2018,"make":"AUDI","model":"TT","trim":"2D CONVERTIBLE","price":25716,"miles":36200,"dev":2625},{"date":"2025-12-15","year":2018,"make":"AUDI","model":"TT","trim":"2D CONVERTIBLE","price":25509,"miles":36200,"dev":2625},{"date":"2025-12-22","year":2018,"make":"AUDI","model":"TT","trim":"2D CONVERTIBLE","price":25298,"miles":36300,"dev":2625},{"date":"2025-12-29","year":2018,"make":"AUDI","model":"TT","trim":"2D CONVERTIBLE","price":25087,"miles":36400,"dev":2625},{"date":"2026-01-05","year":2018,"make":"AUDI","model":"TT","trim":"2D CONVERTIBLE","price":24883,"miles":36400,"dev":2625},{"date":"2026-01-12","year":2018,"make":"AUDI","model":"TT","trim":"2D CONVERTIBLE","price":24692,"miles":36500,"dev":2625},{"date":"2026-01-19","year":2018,"make":"AUDI","model":"TT","trim":"2D CONVERTIBLE","price":24518,"miles":36600,"dev":2625},{"date":"2026-01-26","year":2018,"make":"AUDI","model":"TT","trim":"2D CONVERTIBLE","price":24362,"miles":36600,"dev":2625},{"date":"2026-02-02","year":2018,"make":"AUDI","model":"TT","trim":"2D CONVERTIBLE","price":24224,"miles":36700,"dev":2625},{"date":"2026-02-09","year":2018,"make":"AUDI","model":"TT","trim":"2D CONVERTIBLE","price":24104,"miles":36800,"dev":2625},{"date":"2026-02-16","year":2018,"make":"AUDI","model":"TT","trim":"2D CONVERTIBLE","price":24000,"miles":36800,"dev":2625},{"date":"2026-02-23","year":2018,"make":"AUDI","model":"TT","trim":"2D CONVERTIBLE","price":23910,"miles":36900,"dev":2625},{"date":"2026-03-02","year":2018,"make":"AUDI","model":"TT","trim":"2D CONVERTIBLE","price":23831,"miles":37000,"dev":2625},{"date":"2026-03-09","year":2018,"make":"AUDI","model":"TT","trim":"2D CONVERTIBLE","price":23764,"miles":37000,"dev":2625},{"date":"2026-03-16","year":2018,"make":"AUDI","model":"TT","trim":"2D CONVERTIBLE","price":23706,"miles":37100,"dev":2625},{"date":"2026-03-23","year":2018,"make":"AUDI","model":"TT","trim":"2D CONVERTIBLE","price":23659,"miles":37200,"dev":2625},{"date":"2026-03-30","year":2018,"make":"AUDI","model":"TT","trim":"2D CONVERTIBLE","price":23624,"miles":37200,"dev":2625}]