[{"date":"2024-03-25","year":2022,"make":"CADILLAC","model":"ESCALADE ESV 4WD 6C TDSL","trim":"4D SUV PREMIUM LUXURY","price":80982,"miles":19403,"dev":4436},{"date":"2024-04-01","year":2022,"make":"CADILLAC","model":"ESCALADE ESV 4WD 6C TDSL","trim":"4D SUV PREMIUM LUXURY","price":80816,"miles":19672,"dev":4436},{"date":"2024-04-08","year":2022,"make":"CADILLAC","model":"ESCALADE ESV 4WD 6C TDSL","trim":"4D SUV PREMIUM LUXURY","price":80650,"miles":19962,"dev":4436},{"date":"2024-04-15","year":2022,"make":"CADILLAC","model":"ESCALADE ESV 4WD 6C TDSL","trim":"4D SUV PREMIUM LUXURY","price":80482,"miles":20321,"dev":4436},{"date":"2024-04-22","year":2022,"make":"CADILLAC","model":"ESCALADE ESV 4WD 6C TDSL","trim":"4D SUV PREMIUM LUXURY","price":80313,"miles":20740,"dev":4436},{"date":"2024-04-29","year":2022,"make":"CADILLAC","model":"ESCALADE ESV 4WD 6C TDSL","trim":"4D SUV PREMIUM LUXURY","price":80144,"miles":21143,"dev":4436},{"date":"2024-05-06","year":2022,"make":"CADILLAC","model":"ESCALADE ESV 4WD 6C TDSL","trim":"4D SUV PREMIUM LUXURY","price":79974,"miles":21423,"dev":4436},{"date":"2024-05-13","year":2022,"make":"CADILLAC","model":"ESCALADE ESV 4WD 6C TDSL","trim":"4D SUV PREMIUM LUXURY","price":79802,"miles":21723,"dev":4436},{"date":"2024-05-20","year":2022,"make":"CADILLAC","model":"ESCALADE ESV 4WD 6C TDSL","trim":"4D SUV PREMIUM LUXURY","price":79630,"miles":21997,"dev":4436},{"date":"2024-05-27","year":2022,"make":"CADILLAC","model":"ESCALADE ESV 4WD 6C TDSL","trim":"4D SUV PREMIUM LUXURY","price":79456,"miles":22104,"dev":4436},{"date":"2024-06-03","year":2022,"make":"CADILLAC","model":"ESCALADE ESV 4WD 6C TDSL","trim":"4D SUV PREMIUM LUXURY","price":79281,"miles":22116,"dev":4436},{"date":"2024-06-10","year":2022,"make":"CADILLAC","model":"ESCALADE ESV 4WD 6C TDSL","trim":"4D SUV PREMIUM LUXURY","price":79103,"miles":22214,"dev":4436},{"date":"2024-06-17","year":2022,"make":"CADILLAC","model":"ESCALADE ESV 4WD 6C TDSL","trim":"4D SUV PREMIUM LUXURY","price":78924,"miles":22321,"dev":4436},{"date":"2024-06-24","year":2022,"make":"CADILLAC","model":"ESCALADE ESV 4WD 6C TDSL","trim":"4D SUV PREMIUM LUXURY","price":78742,"miles":22307,"dev":4436},{"date":"2024-07-01","year":2022,"make":"CADILLAC","model":"ESCALADE ESV 4WD 6C TDSL","trim":"4D SUV PREMIUM LUXURY","price":78557,"miles":22615,"dev":4436},{"date":"2024-07-08","year":2022,"make":"CADILLAC","model":"ESCALADE ESV 4WD 6C TDSL","trim":"4D SUV PREMIUM LUXURY","price":78370,"miles":22642,"dev":4436},{"date":"2024-07-15","year":2022,"make":"CADILLAC","model":"ESCALADE ESV 4WD 6C TDSL","trim":"4D SUV PREMIUM LUXURY","price":78181,"miles":22699,"dev":4436},{"date":"2024-07-22","year":2022,"make":"CADILLAC","model":"ESCALADE ESV 4WD 6C TDSL","trim":"4D SUV PREMIUM LUXURY","price":77993,"miles":22268,"dev":4436},{"date":"2024-07-29","year":2022,"make":"CADILLAC","model":"ESCALADE ESV 4WD 6C TDSL","trim":"4D SUV PREMIUM LUXURY","price":77812,"miles":22122,"dev":4436},{"date":"2024-08-05","year":2022,"make":"CADILLAC","model":"ESCALADE ESV 4WD 6C TDSL","trim":"4D SUV PREMIUM LUXURY","price":77645,"miles":21843,"dev":4436},{"date":"2024-08-12","year":2022,"make":"CADILLAC","model":"ESCALADE ESV 4WD 6C TDSL","trim":"4D SUV PREMIUM LUXURY","price":77485,"miles":21794,"dev":4436},{"date":"2024-08-19","year":2022,"make":"CADILLAC","model":"ESCALADE ESV 4WD 6C TDSL","trim":"4D SUV PREMIUM LUXURY","price":77313,"miles":21508,"dev":4436},{"date":"2024-08-26","year":2022,"make":"CADILLAC","model":"ESCALADE ESV 4WD 6C TDSL","trim":"4D SUV PREMIUM LUXURY","price":77122,"miles":21330,"dev":4436},{"date":"2024-09-02","year":2022,"make":"CADILLAC","model":"ESCALADE ESV 4WD 6C TDSL","trim":"4D SUV PREMIUM LUXURY","price":76905,"miles":21161,"dev":4436},{"date":"2024-09-09","year":2022,"make":"CADILLAC","model":"ESCALADE ESV 4WD 6C TDSL","trim":"4D SUV PREMIUM LUXURY","price":76656,"miles":21070,"dev":4436},{"date":"2024-09-16","year":2022,"make":"CADILLAC","model":"ESCALADE ESV 4WD 6C TDSL","trim":"4D SUV PREMIUM LUXURY","price":76377,"miles":21240,"dev":4436},{"date":"2024-09-23","year":2022,"make":"CADILLAC","model":"ESCALADE ESV 4WD 6C TDSL","trim":"4D SUV PREMIUM LUXURY","price":76074,"miles":22059,"dev":4436},{"date":"2024-09-30","year":2022,"make":"CADILLAC","model":"ESCALADE ESV 4WD 6C TDSL","trim":"4D SUV PREMIUM LUXURY","price":75755,"miles":22311,"dev":4436},{"date":"2024-10-07","year":2022,"make":"CADILLAC","model":"ESCALADE ESV 4WD 6C TDSL","trim":"4D SUV PREMIUM LUXURY","price":75429,"miles":22483,"dev":4436},{"date":"2024-10-14","year":2022,"make":"CADILLAC","model":"ESCALADE ESV 4WD 6C TDSL","trim":"4D SUV PREMIUM LUXURY","price":75102,"miles":22580,"dev":4436},{"date":"2024-10-21","year":2022,"make":"CADILLAC","model":"ESCALADE ESV 4WD 6C TDSL","trim":"4D SUV PREMIUM LUXURY","price":74780,"miles":22490,"dev":4436},{"date":"2024-10-28","year":2022,"make":"CADILLAC","model":"ESCALADE ESV 4WD 6C TDSL","trim":"4D SUV PREMIUM LUXURY","price":74464,"miles":22532,"dev":4436},{"date":"2024-11-04","year":2022,"make":"CADILLAC","model":"ESCALADE ESV 4WD 6C TDSL","trim":"4D SUV PREMIUM LUXURY","price":74158,"miles":22672,"dev":4436},{"date":"2024-11-11","year":2022,"make":"CADILLAC","model":"ESCALADE ESV 4WD 6C TDSL","trim":"4D SUV PREMIUM LUXURY","price":73865,"miles":23472,"dev":4436},{"date":"2024-11-18","year":2022,"make":"CADILLAC","model":"ESCALADE ESV 4WD 6C TDSL","trim":"4D SUV PREMIUM LUXURY","price":73583,"miles":22551,"dev":4436},{"date":"2024-11-25","year":2022,"make":"CADILLAC","model":"ESCALADE ESV 4WD 6C TDSL","trim":"4D SUV PREMIUM LUXURY","price":73302,"miles":22518,"dev":4436},{"date":"2024-12-02","year":2022,"make":"CADILLAC","model":"ESCALADE ESV 4WD 6C TDSL","trim":"4D SUV PREMIUM LUXURY","price":73014,"miles":22462,"dev":4436},{"date":"2024-12-09","year":2022,"make":"CADILLAC","model":"ESCALADE ESV 4WD 6C TDSL","trim":"4D SUV PREMIUM LUXURY","price":72712,"miles":22604,"dev":4436},{"date":"2024-12-16","year":2022,"make":"CADILLAC","model":"ESCALADE ESV 4WD 6C TDSL","trim":"4D SUV PREMIUM LUXURY","price":72400,"miles":22677,"dev":4436},{"date":"2024-12-23","year":2022,"make":"CADILLAC","model":"ESCALADE ESV 4WD 6C TDSL","trim":"4D SUV PREMIUM LUXURY","price":72092,"miles":22759,"dev":4436},{"date":"2024-12-30","year":2022,"make":"CADILLAC","model":"ESCALADE ESV 4WD 6C TDSL","trim":"4D SUV PREMIUM LUXURY","price":71803,"miles":23273,"dev":4436},{"date":"2025-01-06","year":2022,"make":"CADILLAC","model":"ESCALADE ESV 4WD 6C TDSL","trim":"4D SUV PREMIUM LUXURY","price":71550,"miles":23075,"dev":4436},{"date":"2025-01-13","year":2022,"make":"CADILLAC","model":"ESCALADE ESV 4WD 6C TDSL","trim":"4D SUV PREMIUM LUXURY","price":71349,"miles":23253,"dev":4436},{"date":"2025-01-20","year":2022,"make":"CADILLAC","model":"ESCALADE ESV 4WD 6C TDSL","trim":"4D SUV PREMIUM LUXURY","price":71208,"miles":23315,"dev":4436},{"date":"2025-01-27","year":2022,"make":"CADILLAC","model":"ESCALADE ESV 4WD 6C TDSL","trim":"4D SUV PREMIUM LUXURY","price":71130,"miles":23411,"dev":4436},{"date":"2025-02-03","year":2022,"make":"CADILLAC","model":"ESCALADE ESV 4WD 6C TDSL","trim":"4D SUV PREMIUM LUXURY","price":71116,"miles":24232,"dev":4436},{"date":"2025-02-10","year":2022,"make":"CADILLAC","model":"ESCALADE ESV 4WD 6C TDSL","trim":"4D SUV PREMIUM LUXURY","price":71163,"miles":24552,"dev":4436},{"date":"2025-02-17","year":2022,"make":"CADILLAC","model":"ESCALADE ESV 4WD 6C TDSL","trim":"4D SUV PREMIUM LUXURY","price":71267,"miles":24859,"dev":4436},{"date":"2025-02-24","year":2022,"make":"CADILLAC","model":"ESCALADE ESV 4WD 6C TDSL","trim":"4D SUV PREMIUM LUXURY","price":71424,"miles":25222,"dev":4436},{"date":"2025-03-03","year":2022,"make":"CADILLAC","model":"ESCALADE ESV 4WD 6C TDSL","trim":"4D SUV PREMIUM LUXURY","price":71629,"miles":25319,"dev":4436},{"date":"2025-03-10","year":2022,"make":"CADILLAC","model":"ESCALADE ESV 4WD 6C TDSL","trim":"4D SUV PREMIUM LUXURY","price":71876,"miles":27355,"dev":4436},{"date":"2025-03-17","year":2022,"make":"CADILLAC","model":"ESCALADE ESV 4WD 6C TDSL","trim":"4D SUV PREMIUM LUXURY","price":72162,"miles":27617,"dev":4436},{"date":"2025-03-24","year":2022,"make":"CADILLAC","model":"ESCALADE ESV 4WD 6C TDSL","trim":"4D SUV PREMIUM LUXURY","price":72483,"miles":29959,"dev":4436},{"date":"2025-03-31","year":2022,"make":"CADILLAC","model":"ESCALADE ESV 4WD 6C TDSL","trim":"4D SUV PREMIUM LUXURY","price":72835,"miles":29473,"dev":4436},{"date":"2025-04-07","year":2022,"make":"CADILLAC","model":"ESCALADE ESV 4WD 6C TDSL","trim":"4D SUV PREMIUM LUXURY","price":73213,"miles":29640,"dev":4436},{"date":"2025-04-14","year":2022,"make":"CADILLAC","model":"ESCALADE ESV 4WD 6C TDSL","trim":"4D SUV PREMIUM LUXURY","price":73608,"miles":29615,"dev":4436},{"date":"2025-04-21","year":2022,"make":"CADILLAC","model":"ESCALADE ESV 4WD 6C TDSL","trim":"4D SUV PREMIUM LUXURY","price":74007,"miles":29706,"dev":4436},{"date":"2025-04-28","year":2022,"make":"CADILLAC","model":"ESCALADE ESV 4WD 6C TDSL","trim":"4D SUV PREMIUM LUXURY","price":74390,"miles":29525,"dev":4436},{"date":"2025-05-05","year":2022,"make":"CADILLAC","model":"ESCALADE ESV 4WD 6C TDSL","trim":"4D SUV PREMIUM LUXURY","price":74736,"miles":29608,"dev":4436},{"date":"2025-05-12","year":2022,"make":"CADILLAC","model":"ESCALADE ESV 4WD 6C TDSL","trim":"4D SUV PREMIUM LUXURY","price":75024,"miles":29782,"dev":4436},{"date":"2025-05-19","year":2022,"make":"CADILLAC","model":"ESCALADE ESV 4WD 6C TDSL","trim":"4D SUV PREMIUM LUXURY","price":75242,"miles":30219,"dev":4436},{"date":"2025-05-26","year":2022,"make":"CADILLAC","model":"ESCALADE ESV 4WD 6C TDSL","trim":"4D SUV PREMIUM LUXURY","price":75380,"miles":30518,"dev":4436},{"date":"2025-06-02","year":2022,"make":"CADILLAC","model":"ESCALADE ESV 4WD 6C TDSL","trim":"4D SUV PREMIUM LUXURY","price":75437,"miles":30832,"dev":4436},{"date":"2025-06-09","year":2022,"make":"CADILLAC","model":"ESCALADE ESV 4WD 6C TDSL","trim":"4D SUV PREMIUM LUXURY","price":75417,"miles":31289,"dev":4436},{"date":"2025-06-16","year":2022,"make":"CADILLAC","model":"ESCALADE ESV 4WD 6C TDSL","trim":"4D SUV PREMIUM LUXURY","price":75330,"miles":31256,"dev":4436},{"date":"2025-06-23","year":2022,"make":"CADILLAC","model":"ESCALADE ESV 4WD 6C TDSL","trim":"4D SUV PREMIUM LUXURY","price":75194,"miles":31347,"dev":4436},{"date":"2025-06-30","year":2022,"make":"CADILLAC","model":"ESCALADE ESV 4WD 6C TDSL","trim":"4D SUV PREMIUM LUXURY","price":75029,"miles":31338,"dev":4436},{"date":"2025-07-07","year":2022,"make":"CADILLAC","model":"ESCALADE ESV 4WD 6C TDSL","trim":"4D SUV PREMIUM LUXURY","price":74856,"miles":31380,"dev":4436},{"date":"2025-07-14","year":2022,"make":"CADILLAC","model":"ESCALADE ESV 4WD 6C TDSL","trim":"4D SUV PREMIUM LUXURY","price":74688,"miles":31436,"dev":4436},{"date":"2025-07-21","year":2022,"make":"CADILLAC","model":"ESCALADE ESV 4WD 6C TDSL","trim":"4D SUV PREMIUM LUXURY","price":74529,"miles":31495,"dev":4436},{"date":"2025-07-28","year":2022,"make":"CADILLAC","model":"ESCALADE ESV 4WD 6C TDSL","trim":"4D SUV PREMIUM LUXURY","price":74371,"miles":31549,"dev":4436},{"date":"2025-08-04","year":2022,"make":"CADILLAC","model":"ESCALADE ESV 4WD 6C TDSL","trim":"4D SUV PREMIUM LUXURY","price":74201,"miles":31731,"dev":4436},{"date":"2025-08-11","year":2022,"make":"CADILLAC","model":"ESCALADE ESV 4WD 6C TDSL","trim":"4D SUV PREMIUM LUXURY","price":74011,"miles":31964,"dev":4436},{"date":"2025-08-18","year":2022,"make":"CADILLAC","model":"ESCALADE ESV 4WD 6C TDSL","trim":"4D SUV PREMIUM LUXURY","price":73795,"miles":32526,"dev":4436},{"date":"2025-08-25","year":2022,"make":"CADILLAC","model":"ESCALADE ESV 4WD 6C TDSL","trim":"4D SUV PREMIUM LUXURY","price":73550,"miles":32877,"dev":4436},{"date":"2025-09-01","year":2022,"make":"CADILLAC","model":"ESCALADE ESV 4WD 6C TDSL","trim":"4D SUV PREMIUM LUXURY","price":73272,"miles":33070,"dev":4436},{"date":"2025-09-08","year":2022,"make":"CADILLAC","model":"ESCALADE ESV 4WD 6C TDSL","trim":"4D SUV PREMIUM LUXURY","price":72958,"miles":33402,"dev":4436},{"date":"2025-09-15","year":2022,"make":"CADILLAC","model":"ESCALADE ESV 4WD 6C TDSL","trim":"4D SUV PREMIUM LUXURY","price":72605,"miles":33711,"dev":4436},{"date":"2025-09-22","year":2022,"make":"CADILLAC","model":"ESCALADE ESV 4WD 6C TDSL","trim":"4D SUV PREMIUM LUXURY","price":72214,"miles":34589,"dev":4436},{"date":"2025-09-29","year":2022,"make":"CADILLAC","model":"ESCALADE ESV 4WD 6C TDSL","trim":"4D SUV PREMIUM LUXURY","price":71785,"miles":34767,"dev":4436},{"date":"2025-10-06","year":2022,"make":"CADILLAC","model":"ESCALADE ESV 4WD 6C TDSL","trim":"4D SUV PREMIUM LUXURY","price":71323,"miles":34927,"dev":4436},{"date":"2025-10-13","year":2022,"make":"CADILLAC","model":"ESCALADE ESV 4WD 6C TDSL","trim":"4D SUV PREMIUM LUXURY","price":70831,"miles":34933,"dev":4436},{"date":"2025-10-20","year":2022,"make":"CADILLAC","model":"ESCALADE ESV 4WD 6C TDSL","trim":"4D SUV PREMIUM LUXURY","price":70312,"miles":35381,"dev":4436},{"date":"2025-10-27","year":2022,"make":"CADILLAC","model":"ESCALADE ESV 4WD 6C TDSL","trim":"4D SUV PREMIUM LUXURY","price":69773,"miles":35784,"dev":4436},{"date":"2025-11-03","year":2022,"make":"CADILLAC","model":"ESCALADE ESV 4WD 6C TDSL","trim":"4D SUV PREMIUM LUXURY","price":69216,"miles":36024,"dev":4436},{"date":"2025-11-10","year":2022,"make":"CADILLAC","model":"ESCALADE ESV 4WD 6C TDSL","trim":"4D SUV PREMIUM LUXURY","price":68648,"miles":36513,"dev":4436},{"date":"2025-11-17","year":2022,"make":"CADILLAC","model":"ESCALADE ESV 4WD 6C TDSL","trim":"4D SUV PREMIUM LUXURY","price":68071,"miles":36787,"dev":4436},{"date":"2025-11-24","year":2022,"make":"CADILLAC","model":"ESCALADE ESV 4WD 6C TDSL","trim":"4D SUV PREMIUM LUXURY","price":67483,"miles":37126,"dev":4436},{"date":"2025-12-01","year":2022,"make":"CADILLAC","model":"ESCALADE ESV 4WD 6C TDSL","trim":"4D SUV PREMIUM LUXURY","price":66882,"miles":37407,"dev":4436},{"date":"2025-12-08","year":2022,"make":"CADILLAC","model":"ESCALADE ESV 4WD 6C TDSL","trim":"4D SUV PREMIUM LUXURY","price":66274,"miles":37615,"dev":4436},{"date":"2025-12-15","year":2022,"make":"CADILLAC","model":"ESCALADE ESV 4WD 6C TDSL","trim":"4D SUV PREMIUM LUXURY","price":65674,"miles":37992,"dev":4436},{"date":"2025-12-22","year":2022,"make":"CADILLAC","model":"ESCALADE ESV 4WD 6C TDSL","trim":"4D SUV PREMIUM LUXURY","price":65103,"miles":38374,"dev":4436},{"date":"2025-12-29","year":2022,"make":"CADILLAC","model":"ESCALADE ESV 4WD 6C TDSL","trim":"4D SUV PREMIUM LUXURY","price":64582,"miles":38807,"dev":4436},{"date":"2026-01-05","year":2022,"make":"CADILLAC","model":"ESCALADE ESV 4WD 6C TDSL","trim":"4D SUV PREMIUM LUXURY","price":64132,"miles":39336,"dev":4436},{"date":"2026-01-12","year":2022,"make":"CADILLAC","model":"ESCALADE ESV 4WD 6C TDSL","trim":"4D SUV PREMIUM LUXURY","price":63771,"miles":39945,"dev":4436},{"date":"2026-01-19","year":2022,"make":"CADILLAC","model":"ESCALADE ESV 4WD 6C TDSL","trim":"4D SUV PREMIUM LUXURY","price":63510,"miles":40166,"dev":4436},{"date":"2026-01-26","year":2022,"make":"CADILLAC","model":"ESCALADE ESV 4WD 6C TDSL","trim":"4D SUV PREMIUM LUXURY","price":63353,"miles":40915,"dev":4436},{"date":"2026-02-02","year":2022,"make":"CADILLAC","model":"ESCALADE ESV 4WD 6C TDSL","trim":"4D SUV PREMIUM LUXURY","price":63299,"miles":41509,"dev":4436},{"date":"2026-02-09","year":2022,"make":"CADILLAC","model":"ESCALADE ESV 4WD 6C TDSL","trim":"4D SUV PREMIUM LUXURY","price":63339,"miles":41563,"dev":4436},{"date":"2026-02-16","year":2022,"make":"CADILLAC","model":"ESCALADE ESV 4WD 6C TDSL","trim":"4D SUV PREMIUM LUXURY","price":63463,"miles":41906,"dev":4436},{"date":"2026-02-23","year":2022,"make":"CADILLAC","model":"ESCALADE ESV 4WD 6C TDSL","trim":"4D SUV PREMIUM LUXURY","price":63661,"miles":42071,"dev":4436},{"date":"2026-03-02","year":2022,"make":"CADILLAC","model":"ESCALADE ESV 4WD 6C TDSL","trim":"4D SUV PREMIUM LUXURY","price":63920,"miles":42231,"dev":4436},{"date":"2026-03-09","year":2022,"make":"CADILLAC","model":"ESCALADE ESV 4WD 6C TDSL","trim":"4D SUV PREMIUM LUXURY","price":64224,"miles":42300,"dev":4436},{"date":"2026-03-16","year":2022,"make":"CADILLAC","model":"ESCALADE ESV 4WD 6C TDSL","trim":"4D SUV PREMIUM LUXURY","price":64557,"miles":42447,"dev":4436},{"date":"2026-03-23","year":2022,"make":"CADILLAC","model":"ESCALADE ESV 4WD 6C TDSL","trim":"4D SUV PREMIUM LUXURY","price":64905,"miles":40266,"dev":4436},{"date":"2026-03-30","year":2022,"make":"CADILLAC","model":"ESCALADE ESV 4WD 6C TDSL","trim":"4D SUV PREMIUM LUXURY","price":65253,"miles":40089,"dev":4436}]