[{"date":"2024-03-25","year":2022,"make":"CHEVROLET","model":"SILVERADO 1500 LTD 4WD V8","trim":"CREW CAB 6.2L RST","price":44963,"miles":26148,"dev":3777},{"date":"2024-04-01","year":2022,"make":"CHEVROLET","model":"SILVERADO 1500 LTD 4WD V8","trim":"CREW CAB 6.2L RST","price":44844,"miles":26510,"dev":3777},{"date":"2024-04-08","year":2022,"make":"CHEVROLET","model":"SILVERADO 1500 LTD 4WD V8","trim":"CREW CAB 6.2L RST","price":44728,"miles":26839,"dev":3777},{"date":"2024-04-15","year":2022,"make":"CHEVROLET","model":"SILVERADO 1500 LTD 4WD V8","trim":"CREW CAB 6.2L RST","price":44617,"miles":27137,"dev":3777},{"date":"2024-04-22","year":2022,"make":"CHEVROLET","model":"SILVERADO 1500 LTD 4WD V8","trim":"CREW CAB 6.2L RST","price":44508,"miles":27406,"dev":3777},{"date":"2024-04-29","year":2022,"make":"CHEVROLET","model":"SILVERADO 1500 LTD 4WD V8","trim":"CREW CAB 6.2L RST","price":44398,"miles":27679,"dev":3777},{"date":"2024-05-06","year":2022,"make":"CHEVROLET","model":"SILVERADO 1500 LTD 4WD V8","trim":"CREW CAB 6.2L RST","price":44289,"miles":27943,"dev":3777},{"date":"2024-05-13","year":2022,"make":"CHEVROLET","model":"SILVERADO 1500 LTD 4WD V8","trim":"CREW CAB 6.2L RST","price":44185,"miles":28199,"dev":3777},{"date":"2024-05-20","year":2022,"make":"CHEVROLET","model":"SILVERADO 1500 LTD 4WD V8","trim":"CREW CAB 6.2L RST","price":44076,"miles":28465,"dev":3777},{"date":"2024-05-27","year":2022,"make":"CHEVROLET","model":"SILVERADO 1500 LTD 4WD V8","trim":"CREW CAB 6.2L RST","price":43967,"miles":28647,"dev":3777},{"date":"2024-06-03","year":2022,"make":"CHEVROLET","model":"SILVERADO 1500 LTD 4WD V8","trim":"CREW CAB 6.2L RST","price":43858,"miles":28853,"dev":3777},{"date":"2024-06-10","year":2022,"make":"CHEVROLET","model":"SILVERADO 1500 LTD 4WD V8","trim":"CREW CAB 6.2L RST","price":43749,"miles":29073,"dev":3777},{"date":"2024-06-17","year":2022,"make":"CHEVROLET","model":"SILVERADO 1500 LTD 4WD V8","trim":"CREW CAB 6.2L RST","price":43639,"miles":29305,"dev":3777},{"date":"2024-06-24","year":2022,"make":"CHEVROLET","model":"SILVERADO 1500 LTD 4WD V8","trim":"CREW CAB 6.2L RST","price":43528,"miles":29522,"dev":3777},{"date":"2024-07-01","year":2022,"make":"CHEVROLET","model":"SILVERADO 1500 LTD 4WD V8","trim":"CREW CAB 6.2L RST","price":43416,"miles":29767,"dev":3777},{"date":"2024-07-08","year":2022,"make":"CHEVROLET","model":"SILVERADO 1500 LTD 4WD V8","trim":"CREW CAB 6.2L RST","price":43303,"miles":30017,"dev":3777},{"date":"2024-07-15","year":2022,"make":"CHEVROLET","model":"SILVERADO 1500 LTD 4WD V8","trim":"CREW CAB 6.2L RST","price":43190,"miles":30266,"dev":3777},{"date":"2024-07-22","year":2022,"make":"CHEVROLET","model":"SILVERADO 1500 LTD 4WD V8","trim":"CREW CAB 6.2L RST","price":43077,"miles":30536,"dev":3777},{"date":"2024-07-29","year":2022,"make":"CHEVROLET","model":"SILVERADO 1500 LTD 4WD V8","trim":"CREW CAB 6.2L RST","price":42971,"miles":30655,"dev":3777},{"date":"2024-08-05","year":2022,"make":"CHEVROLET","model":"SILVERADO 1500 LTD 4WD V8","trim":"CREW CAB 6.2L RST","price":42877,"miles":30927,"dev":3777},{"date":"2024-08-12","year":2022,"make":"CHEVROLET","model":"SILVERADO 1500 LTD 4WD V8","trim":"CREW CAB 6.2L RST","price":42789,"miles":31222,"dev":3777},{"date":"2024-08-19","year":2022,"make":"CHEVROLET","model":"SILVERADO 1500 LTD 4WD V8","trim":"CREW CAB 6.2L RST","price":42691,"miles":31502,"dev":3777},{"date":"2024-08-26","year":2022,"make":"CHEVROLET","model":"SILVERADO 1500 LTD 4WD V8","trim":"CREW CAB 6.2L RST","price":42575,"miles":31885,"dev":3777},{"date":"2024-09-02","year":2022,"make":"CHEVROLET","model":"SILVERADO 1500 LTD 4WD V8","trim":"CREW CAB 6.2L RST","price":42435,"miles":32199,"dev":3777},{"date":"2024-09-09","year":2022,"make":"CHEVROLET","model":"SILVERADO 1500 LTD 4WD V8","trim":"CREW CAB 6.2L RST","price":42265,"miles":32579,"dev":3777},{"date":"2024-09-16","year":2022,"make":"CHEVROLET","model":"SILVERADO 1500 LTD 4WD V8","trim":"CREW CAB 6.2L RST","price":42065,"miles":32955,"dev":3777},{"date":"2024-09-23","year":2022,"make":"CHEVROLET","model":"SILVERADO 1500 LTD 4WD V8","trim":"CREW CAB 6.2L RST","price":41837,"miles":33440,"dev":3777},{"date":"2024-09-30","year":2022,"make":"CHEVROLET","model":"SILVERADO 1500 LTD 4WD V8","trim":"CREW CAB 6.2L RST","price":41588,"miles":33825,"dev":3777},{"date":"2024-10-07","year":2022,"make":"CHEVROLET","model":"SILVERADO 1500 LTD 4WD V8","trim":"CREW CAB 6.2L RST","price":41325,"miles":34479,"dev":3777},{"date":"2024-10-14","year":2022,"make":"CHEVROLET","model":"SILVERADO 1500 LTD 4WD V8","trim":"CREW CAB 6.2L RST","price":41059,"miles":34892,"dev":3777},{"date":"2024-10-21","year":2022,"make":"CHEVROLET","model":"SILVERADO 1500 LTD 4WD V8","trim":"CREW CAB 6.2L RST","price":40798,"miles":35284,"dev":3777},{"date":"2024-10-28","year":2022,"make":"CHEVROLET","model":"SILVERADO 1500 LTD 4WD V8","trim":"CREW CAB 6.2L RST","price":40553,"miles":35622,"dev":3777},{"date":"2024-11-04","year":2022,"make":"CHEVROLET","model":"SILVERADO 1500 LTD 4WD V8","trim":"CREW CAB 6.2L RST","price":40329,"miles":35931,"dev":3777},{"date":"2024-11-11","year":2022,"make":"CHEVROLET","model":"SILVERADO 1500 LTD 4WD V8","trim":"CREW CAB 6.2L RST","price":40133,"miles":36283,"dev":3777},{"date":"2024-11-18","year":2022,"make":"CHEVROLET","model":"SILVERADO 1500 LTD 4WD V8","trim":"CREW CAB 6.2L RST","price":39964,"miles":36623,"dev":3777},{"date":"2024-11-25","year":2022,"make":"CHEVROLET","model":"SILVERADO 1500 LTD 4WD V8","trim":"CREW CAB 6.2L RST","price":39816,"miles":36934,"dev":3777},{"date":"2024-12-02","year":2022,"make":"CHEVROLET","model":"SILVERADO 1500 LTD 4WD V8","trim":"CREW CAB 6.2L RST","price":39684,"miles":37282,"dev":3777},{"date":"2024-12-09","year":2022,"make":"CHEVROLET","model":"SILVERADO 1500 LTD 4WD V8","trim":"CREW CAB 6.2L RST","price":39570,"miles":37577,"dev":3777},{"date":"2024-12-16","year":2022,"make":"CHEVROLET","model":"SILVERADO 1500 LTD 4WD V8","trim":"CREW CAB 6.2L RST","price":39481,"miles":38089,"dev":3777},{"date":"2024-12-23","year":2022,"make":"CHEVROLET","model":"SILVERADO 1500 LTD 4WD V8","trim":"CREW CAB 6.2L RST","price":39431,"miles":38368,"dev":3777},{"date":"2024-12-30","year":2022,"make":"CHEVROLET","model":"SILVERADO 1500 LTD 4WD V8","trim":"CREW CAB 6.2L RST","price":39432,"miles":37669,"dev":3777},{"date":"2025-01-06","year":2022,"make":"CHEVROLET","model":"SILVERADO 1500 LTD 4WD V8","trim":"CREW CAB 6.2L RST","price":39496,"miles":37858,"dev":3777},{"date":"2025-01-13","year":2022,"make":"CHEVROLET","model":"SILVERADO 1500 LTD 4WD V8","trim":"CREW CAB 6.2L RST","price":39632,"miles":37974,"dev":3777},{"date":"2025-01-20","year":2022,"make":"CHEVROLET","model":"SILVERADO 1500 LTD 4WD V8","trim":"CREW CAB 6.2L RST","price":39839,"miles":38157,"dev":3777},{"date":"2025-01-27","year":2022,"make":"CHEVROLET","model":"SILVERADO 1500 LTD 4WD V8","trim":"CREW CAB 6.2L RST","price":40116,"miles":38301,"dev":3777},{"date":"2025-02-03","year":2022,"make":"CHEVROLET","model":"SILVERADO 1500 LTD 4WD V8","trim":"CREW CAB 6.2L RST","price":40452,"miles":38504,"dev":3777},{"date":"2025-02-10","year":2022,"make":"CHEVROLET","model":"SILVERADO 1500 LTD 4WD V8","trim":"CREW CAB 6.2L RST","price":40837,"miles":38592,"dev":3777},{"date":"2025-02-17","year":2022,"make":"CHEVROLET","model":"SILVERADO 1500 LTD 4WD V8","trim":"CREW CAB 6.2L RST","price":41258,"miles":38540,"dev":3777},{"date":"2025-02-24","year":2022,"make":"CHEVROLET","model":"SILVERADO 1500 LTD 4WD V8","trim":"CREW CAB 6.2L RST","price":41258,"miles":38883,"dev":3777},{"date":"2025-03-03","year":2022,"make":"CHEVROLET","model":"SILVERADO 1500 LTD 4WD V8","trim":"CREW CAB 6.2L RST","price":41232,"miles":39122,"dev":3777},{"date":"2025-03-10","year":2022,"make":"CHEVROLET","model":"SILVERADO 1500 LTD 4WD V8","trim":"CREW CAB 6.2L RST","price":41183,"miles":39445,"dev":3777},{"date":"2025-03-17","year":2022,"make":"CHEVROLET","model":"SILVERADO 1500 LTD 4WD V8","trim":"CREW CAB 6.2L RST","price":41110,"miles":39888,"dev":3777},{"date":"2025-03-24","year":2022,"make":"CHEVROLET","model":"SILVERADO 1500 LTD 4WD V8","trim":"CREW CAB 6.2L RST","price":41015,"miles":38713,"dev":3777},{"date":"2025-03-31","year":2022,"make":"CHEVROLET","model":"SILVERADO 1500 LTD 4WD V8","trim":"CREW CAB 6.2L RST","price":40899,"miles":38939,"dev":3777},{"date":"2025-04-07","year":2022,"make":"CHEVROLET","model":"SILVERADO 1500 LTD 4WD V8","trim":"CREW CAB 6.2L RST","price":40762,"miles":39256,"dev":3777},{"date":"2025-04-14","year":2022,"make":"CHEVROLET","model":"SILVERADO 1500 LTD 4WD V8","trim":"CREW CAB 6.2L RST","price":40605,"miles":39433,"dev":3777},{"date":"2025-04-21","year":2022,"make":"CHEVROLET","model":"SILVERADO 1500 LTD 4WD V8","trim":"CREW CAB 6.2L RST","price":40429,"miles":39835,"dev":3777},{"date":"2025-04-28","year":2022,"make":"CHEVROLET","model":"SILVERADO 1500 LTD 4WD V8","trim":"CREW CAB 6.2L RST","price":40236,"miles":40249,"dev":3777},{"date":"2025-05-05","year":2022,"make":"CHEVROLET","model":"SILVERADO 1500 LTD 4WD V8","trim":"CREW CAB 6.2L RST","price":40026,"miles":40533,"dev":3777},{"date":"2025-05-12","year":2022,"make":"CHEVROLET","model":"SILVERADO 1500 LTD 4WD V8","trim":"CREW CAB 6.2L RST","price":39799,"miles":40887,"dev":3777},{"date":"2025-05-19","year":2022,"make":"CHEVROLET","model":"SILVERADO 1500 LTD 4WD V8","trim":"CREW CAB 6.2L RST","price":39558,"miles":40943,"dev":3777},{"date":"2025-05-26","year":2022,"make":"CHEVROLET","model":"SILVERADO 1500 LTD 4WD V8","trim":"CREW CAB 6.2L RST","price":39302,"miles":41102,"dev":3777},{"date":"2025-06-02","year":2022,"make":"CHEVROLET","model":"SILVERADO 1500 LTD 4WD V8","trim":"CREW CAB 6.2L RST","price":39033,"miles":41584,"dev":3777},{"date":"2025-06-09","year":2022,"make":"CHEVROLET","model":"SILVERADO 1500 LTD 4WD V8","trim":"CREW CAB 6.2L RST","price":38751,"miles":41865,"dev":3777},{"date":"2025-06-16","year":2022,"make":"CHEVROLET","model":"SILVERADO 1500 LTD 4WD V8","trim":"CREW CAB 6.2L RST","price":38458,"miles":42122,"dev":3777},{"date":"2025-06-23","year":2022,"make":"CHEVROLET","model":"SILVERADO 1500 LTD 4WD V8","trim":"CREW CAB 6.2L RST","price":38153,"miles":42510,"dev":3777},{"date":"2025-06-30","year":2022,"make":"CHEVROLET","model":"SILVERADO 1500 LTD 4WD V8","trim":"CREW CAB 6.2L RST","price":37839,"miles":42940,"dev":3777},{"date":"2025-07-07","year":2022,"make":"CHEVROLET","model":"SILVERADO 1500 LTD 4WD V8","trim":"CREW CAB 6.2L RST","price":37516,"miles":43397,"dev":3777},{"date":"2025-07-14","year":2022,"make":"CHEVROLET","model":"SILVERADO 1500 LTD 4WD V8","trim":"CREW CAB 6.2L RST","price":37185,"miles":43845,"dev":3777},{"date":"2025-07-21","year":2022,"make":"CHEVROLET","model":"SILVERADO 1500 LTD 4WD V8","trim":"CREW CAB 6.2L RST","price":36847,"miles":44587,"dev":3777},{"date":"2025-07-28","year":2022,"make":"CHEVROLET","model":"SILVERADO 1500 LTD 4WD V8","trim":"CREW CAB 6.2L RST","price":36503,"miles":44880,"dev":3777},{"date":"2025-08-04","year":2022,"make":"CHEVROLET","model":"SILVERADO 1500 LTD 4WD V8","trim":"CREW CAB 6.2L RST","price":36153,"miles":45273,"dev":3777},{"date":"2025-08-11","year":2022,"make":"CHEVROLET","model":"SILVERADO 1500 LTD 4WD V8","trim":"CREW CAB 6.2L RST","price":35799,"miles":45593,"dev":3777},{"date":"2025-08-18","year":2022,"make":"CHEVROLET","model":"SILVERADO 1500 LTD 4WD V8","trim":"CREW CAB 6.2L RST","price":35441,"miles":46172,"dev":3777},{"date":"2025-08-25","year":2022,"make":"CHEVROLET","model":"SILVERADO 1500 LTD 4WD V8","trim":"CREW CAB 6.2L RST","price":35080,"miles":46561,"dev":3777},{"date":"2025-09-01","year":2022,"make":"CHEVROLET","model":"SILVERADO 1500 LTD 4WD V8","trim":"CREW CAB 6.2L RST","price":34718,"miles":47152,"dev":3777},{"date":"2025-09-08","year":2022,"make":"CHEVROLET","model":"SILVERADO 1500 LTD 4WD V8","trim":"CREW CAB 6.2L RST","price":34355,"miles":47682,"dev":3777},{"date":"2025-09-15","year":2022,"make":"CHEVROLET","model":"SILVERADO 1500 LTD 4WD V8","trim":"CREW CAB 6.2L RST","price":33991,"miles":48238,"dev":3777},{"date":"2025-09-22","year":2022,"make":"CHEVROLET","model":"SILVERADO 1500 LTD 4WD V8","trim":"CREW CAB 6.2L RST","price":33629,"miles":48849,"dev":3777},{"date":"2025-09-29","year":2022,"make":"CHEVROLET","model":"SILVERADO 1500 LTD 4WD V8","trim":"CREW CAB 6.2L RST","price":33268,"miles":49434,"dev":3777},{"date":"2025-10-06","year":2022,"make":"CHEVROLET","model":"SILVERADO 1500 LTD 4WD V8","trim":"CREW CAB 6.2L RST","price":32910,"miles":49947,"dev":3777},{"date":"2025-10-13","year":2022,"make":"CHEVROLET","model":"SILVERADO 1500 LTD 4WD V8","trim":"CREW CAB 6.2L RST","price":32555,"miles":50345,"dev":3777},{"date":"2025-10-20","year":2022,"make":"CHEVROLET","model":"SILVERADO 1500 LTD 4WD V8","trim":"CREW CAB 6.2L RST","price":32205,"miles":50676,"dev":3777},{"date":"2025-10-27","year":2022,"make":"CHEVROLET","model":"SILVERADO 1500 LTD 4WD V8","trim":"CREW CAB 6.2L RST","price":31860,"miles":51119,"dev":3777},{"date":"2025-11-03","year":2022,"make":"CHEVROLET","model":"SILVERADO 1500 LTD 4WD V8","trim":"CREW CAB 6.2L RST","price":31522,"miles":51530,"dev":3777},{"date":"2025-11-10","year":2022,"make":"CHEVROLET","model":"SILVERADO 1500 LTD 4WD V8","trim":"CREW CAB 6.2L RST","price":31190,"miles":51906,"dev":3777},{"date":"2025-11-17","year":2022,"make":"CHEVROLET","model":"SILVERADO 1500 LTD 4WD V8","trim":"CREW CAB 6.2L RST","price":30867,"miles":52554,"dev":3777},{"date":"2025-11-24","year":2022,"make":"CHEVROLET","model":"SILVERADO 1500 LTD 4WD V8","trim":"CREW CAB 6.2L RST","price":30552,"miles":53096,"dev":3777},{"date":"2025-12-01","year":2022,"make":"CHEVROLET","model":"SILVERADO 1500 LTD 4WD V8","trim":"CREW CAB 6.2L RST","price":30248,"miles":53536,"dev":3777},{"date":"2025-12-08","year":2022,"make":"CHEVROLET","model":"SILVERADO 1500 LTD 4WD V8","trim":"CREW CAB 6.2L RST","price":29953,"miles":54228,"dev":3777},{"date":"2025-12-15","year":2022,"make":"CHEVROLET","model":"SILVERADO 1500 LTD 4WD V8","trim":"CREW CAB 6.2L RST","price":29671,"miles":54636,"dev":3777},{"date":"2025-12-22","year":2022,"make":"CHEVROLET","model":"SILVERADO 1500 LTD 4WD V8","trim":"CREW CAB 6.2L RST","price":29401,"miles":54869,"dev":3777},{"date":"2025-12-29","year":2022,"make":"CHEVROLET","model":"SILVERADO 1500 LTD 4WD V8","trim":"CREW CAB 6.2L RST","price":29144,"miles":55337,"dev":3777},{"date":"2026-01-05","year":2022,"make":"CHEVROLET","model":"SILVERADO 1500 LTD 4WD V8","trim":"CREW CAB 6.2L RST","price":28902,"miles":55654,"dev":3777},{"date":"2026-01-12","year":2022,"make":"CHEVROLET","model":"SILVERADO 1500 LTD 4WD V8","trim":"CREW CAB 6.2L RST","price":28674,"miles":55844,"dev":3777},{"date":"2026-01-19","year":2022,"make":"CHEVROLET","model":"SILVERADO 1500 LTD 4WD V8","trim":"CREW CAB 6.2L RST","price":28463,"miles":56265,"dev":3777},{"date":"2026-01-26","year":2022,"make":"CHEVROLET","model":"SILVERADO 1500 LTD 4WD V8","trim":"CREW CAB 6.2L RST","price":28269,"miles":56377,"dev":3777},{"date":"2026-02-02","year":2022,"make":"CHEVROLET","model":"SILVERADO 1500 LTD 4WD V8","trim":"CREW CAB 6.2L RST","price":28092,"miles":56445,"dev":3777},{"date":"2026-02-09","year":2022,"make":"CHEVROLET","model":"SILVERADO 1500 LTD 4WD V8","trim":"CREW CAB 6.2L RST","price":27934,"miles":56484,"dev":3777},{"date":"2026-02-16","year":2022,"make":"CHEVROLET","model":"SILVERADO 1500 LTD 4WD V8","trim":"CREW CAB 6.2L RST","price":27796,"miles":56706,"dev":3777},{"date":"2026-02-23","year":2022,"make":"CHEVROLET","model":"SILVERADO 1500 LTD 4WD V8","trim":"CREW CAB 6.2L RST","price":27678,"miles":57026,"dev":3777},{"date":"2026-03-02","year":2022,"make":"CHEVROLET","model":"SILVERADO 1500 LTD 4WD V8","trim":"CREW CAB 6.2L RST","price":27582,"miles":57171,"dev":3777},{"date":"2026-03-09","year":2022,"make":"CHEVROLET","model":"SILVERADO 1500 LTD 4WD V8","trim":"CREW CAB 6.2L RST","price":27507,"miles":57108,"dev":3777},{"date":"2026-03-16","year":2022,"make":"CHEVROLET","model":"SILVERADO 1500 LTD 4WD V8","trim":"CREW CAB 6.2L RST","price":27627,"miles":57061,"dev":3777},{"date":"2026-03-23","year":2022,"make":"CHEVROLET","model":"SILVERADO 1500 LTD 4WD V8","trim":"CREW CAB 6.2L RST","price":28130,"miles":55510,"dev":3777},{"date":"2026-03-30","year":2022,"make":"CHEVROLET","model":"SILVERADO 1500 LTD 4WD V8","trim":"CREW CAB 6.2L RST","price":28555,"miles":55819,"dev":3777}]